{
  "family": "hexacode-prod-submission-service",
  "taskRoleArn": "arn:aws:iam::380825342853:role/hexacode-prod-submission-task",
  "executionRoleArn": "arn:aws:iam::380825342853:role/hexacode-prod-ecs-execution",
  "networkMode": "awsvpc",
  "containerDefinitions": [
    {
      "name": "submission-service",
      "image": "380825342853.dkr.ecr.us-west-2.amazonaws.com/prod/hexacode:submission-service-20260424-102200",
      "cpu": 0,
      "portMappings": [
        {
          "containerPort": 8000,
          "hostPort": 8000,
          "protocol": "tcp"
        }
      ],
      "essential": true,
      "environment": [
        {
          "name": "CORS_ALLOW_ORIGINS",
          "value": "https://d2x2kyi0hl9xxu.cloudfront.net,http://localhost:5173,http://127.0.0.1:5173"
        },
        {
          "name": "AWS_REGION",
          "value": "us-west-2"
        },
        {
          "name": "S3_REGION",
          "value": "us-west-2"
        },
        {
          "name": "STORAGE_DRIVER",
          "value": "s3"
        },
        {
          "name": "SQS_ENDPOINT",
          "value": ""
        },
        {
          "name": "COGNITO_ISSUER",
          "value": "https://cognito-idp.us-west-2.amazonaws.com/us-west-2_LryzWA0j5"
        },
        {
          "name": "S3_ENDPOINT",
          "value": ""
        },
        {
          "name": "COGNITO_USER_POOL_ID",
          "value": "us-west-2_LryzWA0j5"
        },
        {
          "name": "S3_BUCKET_PROBLEMS",
          "value": "hexacode-prod-problem-assets-380825342853-us-west-2-an"
        },
        {
          "name": "QUEUE_DRIVER",
          "value": "sqs"
        },
        {
          "name": "S3_BUCKET_SUBMISSIONS",
          "value": "hexacode-prod-submission-artifacts-380825342853-us-west-2-an"
        },
        {
          "name": "SQS_JUDGE_QUEUE_URL",
          "value": "https://sqs.us-west-2.amazonaws.com/380825342853/hexacode-prod-judge-jobs"
        },
        {
          "name": "COGNITO_JWKS_URL",
          "value": "https://cognito-idp.us-west-2.amazonaws.com/us-west-2_LryzWA0j5/.well-known/jwks.json"
        },
        {
          "name": "PROBLEM_SERVICE_URL",
          "value": "http://internal-hexacode-ialb-1835698292.us-west-2.elb.amazonaws.com"
        },
        {
          "name": "COGNITO_APP_CLIENT_ID",
          "value": "7gf3q194gkpg30fbjhriq1t2v0"
        },
        {
          "name": "S3_FORCE_PATH_STYLE",
          "value": "false"
        },
        {
          "name": "LOG_LEVEL",
          "value": "INFO"
        }
      ],
      "mountPoints": [],
      "volumesFrom": [],
      "secrets": [
        {
          "name": "DATABASE_URL",
          "valueFrom": "arn:aws:secretsmanager:us-west-2:380825342853:secret:hexacode-prod-V7OL5l:DATABASE_URL::"
        }
      ],
      "logConfiguration": {
        "logDriver": "awslogs",
        "options": {
          "awslogs-group": "/ecs/hexacode-prod/submission-service",
          "awslogs-region": "us-west-2",
          "awslogs-stream-prefix": "ecs"
        }
      },
      "systemControls": []
    }
  ],
  "volumes": [],
  "placementConstraints": [],
  "requiresCompatibilities": [
    "FARGATE"
  ],
  "cpu": "2048",
  "memory": "4096",
  "runtimePlatform": {
    "cpuArchitecture": "X86_64",
    "operatingSystemFamily": "LINUX"
  }
}
